{
	"class" : {
		"hasDashboard" : "AZ 6/1/2017 22:40",
		"hasDashboard:" : "AZ 6/1/2017 22:37",
		"open" : "jh 6/5/2017 16:36" },
	"instance" : {
		"activateWindow" : "adz 6/15/2017 20:23",
		"activateWindowFromEvent:thumbnail:" : "adz 6/16/2017 20:30",
		"addNumberToVisualization:colored:" : "adz 7/21/2017 15:04",
		"addThumbnailsToCurrentPage" : "adz 7/23/2017 12:04",
		"closeWindow" : "adz 7/25/2017 11:45",
		"currentPage" : "adz 7/6/2017 15:16",
		"currentPage:" : "adz 7/6/2017 15:16",
		"defaultVisualizationExtent" : "adz 7/21/2017 15:01",
		"defaultVisualizationPosition" : "adz 7/21/2017 15:02",
		"delete" : "adz 7/18/2017 00:04",
		"deletePageInVisualization:" : "adz 7/23/2017 12:13",
		"deleteThumbnailsOnCurrentPage" : "adz 7/23/2017 12:03",
		"drawOn:" : "adz 7/23/2017 12:37",
		"equatePageInVisualization" : "adz 7/23/2017 12:17",
		"firstPage" : "adz 7/21/2017 15:11",
		"getWindowsInCurrentSpace" : "adz 7/23/2017 12:50",
		"highlightPageInVisualiszation" : "adz 7/23/2017 12:10",
		"initialize" : "adz 7/23/2017 12:26",
		"initializeLabelMorph:" : "adz 7/23/2017 12:24",
		"initializePageDictionary:" : "adz 7/23/2017 12:28",
		"initializeSelectionRectangle" : "adz 7/6/2017 16:08",
		"initializeThumbnails" : "adz 7/23/2017 12:30",
		"initializeVisualization" : "adz 7/21/2017 15:05",
		"intoWorld:" : "adz 7/10/2017 22:22",
		"lastPage" : "adz 7/21/2017 15:11",
		"lastWindowOnPage:" : "adz 7/24/2017 12:59",
		"nextPage" : "adz 7/23/2017 12:10",
		"numberOfWindowsOnPage" : "adz 7/18/2017 09:27",
		"numberOfWindowsOnPage:" : "adz 7/10/2017 21:33",
		"numberPages" : "adz 7/6/2017 15:22",
		"pageDict" : "adz 7/6/2017 12:04",
		"pageDict:" : "adz 7/6/2017 12:04",
		"previousPage" : "adz 7/23/2017 12:11",
		"selectNextWindow" : "adz 7/17/2017 21:44",
		"selectPreviousWindow" : "adz 7/17/2017 21:44",
		"selectWindow:" : "adz 7/6/2017 14:15",
		"selectWindowFromEvent:thumbnail:" : "jh 5/16/2017 12:13",
		"selectedWindow" : "jh 5/16/2017 12:13",
		"setVisualizationLayout" : "adz 7/21/2017 15:03",
		"thumbnailsOnPage" : "adz 7/6/2017 14:11",
		"updateLayout" : "adz 7/23/2017 12:42",
		"visualization" : "adz 7/17/2017 23:21",
		"visualization:" : "adz 7/17/2017 23:21",
		"windowFromNextPage:" : "adz 7/23/2017 12:38" } }
